mip_helper/__init__.py
mip_helper/errors.py
mip_helper/io_helper.py
mip_helper/models.py
mip_helper/parameters.py
mip_helper/shapes.py
mip_helper/testing.py
mip_helper/utils.py
mip_helper-0.7.8.dist-info/METADATA
mip_helper-0.7.8.dist-info/RECORD
mip_helper-0.7.8.dist-info/WHEEL
mip_helper-0.7.8.dist-info/top_level.txt
