Metadata-Version: 2.1
Name: mip-helper
Version: 0.7.8
Summary: Read/Write inputs/outputs from/to the MIP
Home-page: https://github.com/LREN-CHUV/python-base-docker-images
Author: Mirco Nasuti
Author-email: mirco.nasuti@chuv.ch
License: Apache 2.0
Platform: UNKNOWN
Classifier: Intended Audience :: Developers
Classifier: Intended Audience :: Science/Research
Classifier: Operating System :: Unix
Classifier: License :: OSI Approved :: Apache Software License
Classifier: Topic :: Scientific/Engineering :: Bio-Informatics
Classifier: Programming Language :: Python :: 3 :: Only
Classifier: Programming Language :: Python :: 3.6
Provides-Extra: test
Requires-Dist: psycopg2-binary (==2.7.4)
Requires-Dist: sqlalchemy (==1.2.5)
Requires-Dist: numpy (==1.14.2)
Requires-Dist: pandas (==0.22.0)
Requires-Dist: raven (==6.7.0)
Provides-Extra: test
Requires-Dist: unittest; extra == 'test'
Requires-Dist: nose; extra == 'test'
